smart_geocubes/__init__.py
smart_geocubes/_storage.py
smart_geocubes/exceptions.py
smart_geocubes/py.typed
smart_geocubes/_concurrency/__init__.py
smart_geocubes/_concurrency/threading.py
smart_geocubes/accessors/__init__.py
smart_geocubes/accessors/base.py
smart_geocubes/accessors/gee.py
smart_geocubes/accessors/stac.py
smart_geocubes/datasets/__init__.py
smart_geocubes/datasets/arcticdem.py
smart_geocubes/datasets/tctrend.py
smart_geocubes-0.0.9.dist-info/METADATA
smart_geocubes-0.0.9.dist-info/WHEEL
smart_geocubes-0.0.9.dist-info/licenses/LICENSE
smart_geocubes-0.0.9.dist-info/RECORD
